acfo/__init__.py
acfo/acfo.py
acfo-1.0.0.dist-info/METADATA
acfo-1.0.0.dist-info/WHEEL
acfo-1.0.0.dist-info/licenses/LICENSE
acfo-1.0.0.dist-info/RECORD
