Metadata-Version: 2.4
Name: acfo
Version: 1.0.0
Summary: Adaptive Code Flow Optimizer for Python
Project-URL: Homepage, https://github.com/dev-queiroz/acfo
Project-URL: Issues, https://github.com/dev-queiroz/acfo/issues
Author-email: Douglas Vinícios dos Santos Queiroz <dev.queiroz05@gmail.com>
License-Expression: MIT
License-File: LICENSE
Keywords: code-flow,dependencies,optimization,python
Classifier: License :: OSI Approved :: MIT License
Classifier: Operating System :: OS Independent
Classifier: Programming Language :: Python :: 3
Requires-Python: >=3.6
